gandan/Gandan.py
gandan/GandanCallback.py
gandan/GandanMsg.py
gandan/GandanPub.py
gandan/GandanSub.py
gandan/GandanSubscription.py
gandan/MMAP.py
gandan/__init__.py
gandan-0.4.0.dist-info/METADATA
gandan-0.4.0.dist-info/WHEEL
gandan-0.4.0.dist-info/top_level.txt
gandan-0.4.0.dist-info/RECORD
